[
    {
        "title": "Virtual Production at Stargate Studios",
        "url": "https://www.fxguide.com/quicktakes/virtual-production-at-stargate-studios/",
        "imgUrl": "https://www.fxguide.com/wp-content/uploads/2021/03/VP_stargate-320x160.jpg",
        "description": "Stargate test Tru-vision with URSA Mini Pro 12K cameras.Read ",
        "type": "Article",
        "date": "2021-03-29T20:05:07.012Z"
    },
    {
        "title": "Vision getting ahead in WandaVision",
        "url": "https://www.fxguide.com/fxfeatured/vision-getting-ahead-in-wandavision/",
        "imgUrl": "https://www.fxguide.com/wp-content/uploads/2021/03/Vision1featured-320x160.jpg",
        "description": "A detailed look at Vision facing Wanda’s Westview with VFX Supervisor Tara DeMarco & Rodeo FX’s Julien Héry Read ",
        "type": "Article",
        "date": "2021-03-29T20:05:07.013Z"
    },
    {
        "title": "The Rise of Real-Time Digital Humans: Pulse Panel",
        "url": "https://www.fxguide.com/fxfeatured/the-rise-of-real-time-digital-humans-pulse-panel/",
        "imgUrl": "https://www.fxguide.com/wp-content/uploads/2021/03/pulse51-320x160.jpg",
        "description": "Digital Humans: Pulse Panel including bonus material.Read ",
        "type": "Article",
        "date": "2021-03-29T20:05:07.013Z"
    },
    {
        "title": "Oscars Nominees 2021",
        "url": "https://www.fxguide.com/quicktakes/oscars-nominees-2021/",
        "imgUrl": "https://www.fxguide.com/wp-content/uploads/2021/03/oscars-320x160.jpg",
        "description": "The list of 2021 Oscar Nominees.Read ",
        "type": "Article",
        "date": "2021-03-29T20:05:07.014Z"
    },
    {
        "title": "DI4D extends with PURE4D",
        "url": "https://www.fxguide.com/quicktakes/di4d-extends-with-pure4d/",
        "imgUrl": "https://www.fxguide.com/wp-content/uploads/2021/03/D14D_1-320x160.jpg",
        "description": "Exclusive: DI4D releases PURE4D AI for large volume games charactersRead ",
        "type": "Article",
        "date": "2021-03-29T20:05:07.014Z"
    },
    {
        "title": "Mank’s Monochrome Effects",
        "url": "https://www.fxguide.com/quicktakes/manks-monochrome-effects/",
        "imgUrl": "https://www.fxguide.com/wp-content/uploads/2021/03/mank_featured2-320x160.jpg",
        "description": "Mank is a monochrome love letter to early cinema and some early VFX approaches.Read ",
        "type": "Article",
        "date": "2021-03-29T20:05:07.015Z"
    },
    {
        "title": "Sony Imageworks Character Animation is Over the Moon",
        "url": "https://www.fxguide.com/fxfeatured/sony-imageworks-character-animation-is-over-the-moon/",
        "imgUrl": "https://www.fxguide.com/wp-content/uploads/2021/03/moon-320x160.jpg",
        "description": "Exclusive BTS videos and look at the character animation in Netflix’s Over the MoonRead ",
        "type": "Article",
        "date": "2021-03-29T20:05:07.016Z"
    },
    {
        "title": "Disguising Virtual Production Rendering",
        "url": "https://www.fxguide.com/fxfeatured/disgusing-virtual-production-rendering/",
        "imgUrl": "https://www.fxguide.com/wp-content/uploads/2021/03/disquise2-320x160.jpg",
        "description": "A deep dive on disguise’s cluster rendering and advances for virtual productionRead ",
        "type": "Article",
        "date": "2021-03-29T20:05:07.016Z"
    },
    {
        "title": "Character Integration in Monster Hunter",
        "url": "https://www.fxguide.com/fxfeatured/character-integration-in-monster-hunter/",
        "imgUrl": "https://www.fxguide.com/wp-content/uploads/2021/02/PC0510_comp_v008.1097-copy-320x133.jpg",
        "description": "Ayo Burgess at Mr X, discusses the art of creature live-action digital integration.Read ",
        "type": "Article",
        "date": "2021-03-29T20:05:07.017Z"
    },
    {
        "title": "fxpodcast #327: The Mill",
        "url": "https://www.fxguide.com/fxpodcasts/fxpodcast-327-the-mill/",
        "imgUrl": "https://www.fxguide.com/wp-content/uploads/2021/02/themill2-320x160.jpg",
        "description": "We speak to the new CEO of The Mill about the companies new broader creative direction Read ",
        "type": "Article",
        "date": "2021-03-29T20:05:07.018Z"
    },
    {
        "title": "Head Mounted Sci-Tech Oscars",
        "url": "https://www.fxguide.com/fxfeatured/head-mounted-sci-tech-oscars/",
        "imgUrl": "https://www.fxguide.com/wp-content/uploads/2021/02/hmc1-320x160.jpg",
        "description": "A detailed look at the Sci-Tech winning world of head-mounted cameras and facial MoCap.Read ",
        "type": "Article",
        "date": "2021-03-29T20:05:07.018Z"
    },
    {
        "title": "Faceware Studio in 2021",
        "url": "https://www.fxguide.com/quicktakes/faceware-studio-in-2021/",
        "imgUrl": "https://www.fxguide.com/wp-content/uploads/2021/02/faceware_featured-320x160.jpg",
        "description": "We road test the Faceware Studio RigRead ",
        "type": "Article",
        "date": "2021-03-29T20:05:07.019Z"
    },
    {
        "title": "Frame.io straight to the cloud",
        "url": "https://www.fxguide.com/quicktakes/frame-io-straight-to-the-cloud/",
        "imgUrl": "https://www.fxguide.com/wp-content/uploads/2021/02/frameio-320x160.jpg",
        "description": "Film straight to the cloudRead ",
        "type": "Article",
        "date": "2021-03-29T20:05:07.019Z"
    },
    {
        "title": "Mandalorian Season 2 Virtual Production Innovations",
        "url": "https://www.fxguide.com/fxfeatured/mandalorian-season-2-virtual-production-innovations/",
        "imgUrl": "https://www.fxguide.com/wp-content/uploads/2021/02/Mando_featured-320x160.jpg",
        "description": "Virtual Production Innovations from the LED Stages of The Mandalorian.Read ",
        "type": "Article",
        "date": "2021-03-29T20:05:07.019Z"
    },
    {
        "title": "Epic Games Announces MetaHuman",
        "url": "https://www.fxguide.com/quicktakes/epic-games-announces-metahuman/",
        "imgUrl": "https://www.fxguide.com/wp-content/uploads/2021/02/MetaHuman_Creator_key_art_1920x1080-320x180.jpg",
        "description": "Epic Games launches the new streaming MetaHuman CreatorRead ",
        "type": "Article",
        "date": "2021-03-29T20:05:07.020Z"
    },
    {
        "title": "Oscar Short list",
        "url": "https://www.fxguide.com/quicktakes/oscar-short-list/",
        "imgUrl": "https://www.fxguide.com/wp-content/uploads/2019/02/oscarsoutside-320x164.jpg",
        "description": "The 2021 shortlist for Nominations for the 93rd Academy Awards in VFX and Animated Short FilmRead ",
        "type": "Article",
        "date": "2021-03-29T20:05:07.021Z"
    },
    {
        "title": "Digital Humans in Retail",
        "url": "https://www.fxguide.com/fxfeatured/digital-humans-in-retail/",
        "imgUrl": "https://www.fxguide.com/wp-content/uploads/2021/02/fashion-320x160.jpg",
        "subTitle": "ZOZO Jpan pushes extensive Digital Human research for new online retail customer experiences. Read ",
        "type": "Article",
        "date": "2021-03-29T18:36:07.195Z"
    }
]